functown/__init__.py
functown/args/__init__.py
functown/args/args_decorator.py
functown/args/handler.py
functown/auth/__init__.py
functown/auth/auth_decorator.py
functown/auth/jwt.py
functown/errors/__init__.py
functown/errors/error_decorator.py
functown/errors/errors.py
functown/insights/__init__.py
functown/insights/all_decorator.py
functown/insights/base.py
functown/insights/callbacks.py
functown/insights/event_decorator.py
functown/insights/logger_decorator.py
functown/insights/metric_decorator.py
functown/insights/metrics.py
functown/insights/tracer_decorator.py
functown/serialization/__init__.py
functown/serialization/base.py
functown/serialization/dataframe.py
functown/serialization/flatbuf.py
functown/serialization/hybrid.py
functown/serialization/json.py
functown/serialization/protobuf.py
functown/utils/__init__.py
functown/utils/base_decorator.py
functown/utils/flags.py
functown/utils/logging.py
functown/utils/metaclasses.py
functown/utils/stack_decorator.py
functown-2.3.3.dist-info/LICENSE
functown-2.3.3.dist-info/METADATA
functown-2.3.3.dist-info/WHEEL
functown-2.3.3.dist-info/top_level.txt
functown-2.3.3.dist-info/RECORD
