Metadata-Version: 2.1
Name: functown
Version: 2.3.3
Summary: Various Helper Tools to make working with azure functions easier
Home-page: https://github.com/felixnext/python-functown
Download-URL: https://github.com/felixnext/python-functown/releases/tag/v0.1.0-alpha
Author: Felix Geilert
License: MIT License
Keywords: azure functions
Classifier: Development Status :: 4 - Beta
Classifier: Intended Audience :: Developers
Classifier: License :: OSI Approved :: MIT License
Classifier: Programming Language :: Python :: 3
Classifier: Programming Language :: Python :: 3.7
Classifier: Programming Language :: Python :: 3.8
Classifier: Programming Language :: Python :: 3.9
Classifier: Programming Language :: Python :: 3.10
Classifier: Programming Language :: Python :: 3.11
License-File: LICENSE
Requires-Dist: azure-functions >=1.10.1
Requires-Dist: requests >=2.27.1
Provides-Extra: flatbuffer
Requires-Dist: flatbuffers ; extra == 'flatbuffer'
Provides-Extra: insights
Requires-Dist: opencensus-ext-azure >=1.1.8 ; extra == 'insights'
Provides-Extra: jwt
Requires-Dist: cryptography >=36.0.2 ; extra == 'jwt'
Requires-Dist: python-jose >=3.3.0 ; extra == 'jwt'
Provides-Extra: pandas
Requires-Dist: pandas >=0.20.3 ; extra == 'pandas'
Requires-Dist: pyarrow >=0.8.0 ; extra == 'pandas'
Provides-Extra: protobuf
Requires-Dist: protobuf ; extra == 'protobuf'
